globee/__init__.py
globee/admin.py
globee/apps.py
globee/core.py
globee/models.py
globee/signals.py
globee/tests.py
globee/urls.py
globee/views.py
globee/migrations/0001_initial.py
globee/migrations/0002_auto_20180727_0214.py
globee/migrations/0003_auto_20181117_2318.py
globee/migrations/__init__.py
django_globee-1.5.0.dist-info/LICENSE
django_globee-1.5.0.dist-info/METADATA
django_globee-1.5.0.dist-info/WHEEL
django_globee-1.5.0.dist-info/top_level.txt
django_globee-1.5.0.dist-info/RECORD
