Metadata-Version: 2.1
Name: django-globee
Version: 1.5.0
Summary: A Django app for integrating Globee Payments
Home-page: https://github.com/lovvskillz/django-globee
Author: Vadim Zifra
Author-email: vadim@minehub.de
License: MIT License
Platform: UNKNOWN
Classifier: Environment :: Web Environment
Classifier: Framework :: Django
Classifier: Framework :: Django :: 2.0
Classifier: Framework :: Django :: 2.1
Classifier: Framework :: Django :: 2.2
Classifier: Intended Audience :: Developers
Classifier: License :: OSI Approved :: MIT License
Classifier: Operating System :: OS Independent
Classifier: Programming Language :: Python
Classifier: Programming Language :: Python :: 3.5
Classifier: Programming Language :: Python :: 3.6
Classifier: Programming Language :: Python :: 3.7
Classifier: Topic :: Internet :: WWW/HTTP
Classifier: Topic :: Internet :: WWW/HTTP :: Dynamic Content
Requires-Dist: Django (>=2.0)
Requires-Dist: six (>=1.4.1)
Requires-Dist: requests (>=2.19.1)
Requires-Dist: pytz (>=2018.5)
